fluent_checks/__init__.py
fluent_checks/py.typed
fluent_checks-0.3.0.dist-info/WHEEL
fluent_checks-0.3.0.dist-info/METADATA
fluent_checks-0.3.0.dist-info/RECORD
